msgtrace/__init__.py
msgtrace/version.py
msgtrace/sdk/__init__.py
msgtrace/sdk/attributes.py
msgtrace/sdk/spans.py
msgtrace/sdk/tracer.py
msgtrace_sdk-1.1.0.dist-info/METADATA
msgtrace_sdk-1.1.0.dist-info/WHEEL
msgtrace_sdk-1.1.0.dist-info/licenses/LICENSE
msgtrace_sdk-1.1.0.dist-info/RECORD
