Metadata-Version: 2.4
Name: msgtrace-sdk
Version: 1.1.0
Summary: OpenTelemetry-based tracing SDK for AI applications
Author-email: Vilson Rodrigues <vilson@msgflux.com>
License: MIT
License-File: LICENSE
Requires-Python: >=3.10
Requires-Dist: opentelemetry-api>=1.20.0
Requires-Dist: opentelemetry-exporter-otlp-proto-http>=1.20.0
Requires-Dist: opentelemetry-sdk>=1.20.0
